setup.py
alfred/__init__.py
alfred/alfred.py
alfred/modules/__init__.py
alfred/modules/scrap/__init__.py
alfred/modules/scrap/image_scraper.py
alfred/modules/scrap/scraper_images.py
alfred/modules/text/__init__.py
alfred/modules/vision/__init__.py
alfred/modules/vision/video_extractor.py
alfred_collection.egg-info/PKG-INFO
alfred_collection.egg-info/SOURCES.txt
alfred_collection.egg-info/dependency_links.txt
alfred_collection.egg-info/entry_points.txt
alfred_collection.egg-info/requires.txt
alfred_collection.egg-info/top_level.txt